automatic_warehouse/__about__.py
automatic_warehouse/__init__.py
automatic_warehouse/configuration_validator.py
automatic_warehouse/env_vars.py
automatic_warehouse/warehouse.py
automatic_warehouse/warehouse_configuration_singleton.py
automatic_warehouse/simulation/__init__.py
automatic_warehouse/simulation/simulation.py
automatic_warehouse/simulation/actions/__init__.py
automatic_warehouse/simulation/actions/action.py
automatic_warehouse/simulation/actions/action_enum.py
automatic_warehouse/simulation/actions/buffer.py
automatic_warehouse/simulation/actions/extract_tray.py
automatic_warehouse/simulation/actions/send_back_tray.py
automatic_warehouse/simulation/actions/material/__init__.py
automatic_warehouse/simulation/actions/material/insert_material/__init__.py
automatic_warehouse/simulation/actions/material/insert_material/insert_material.py
automatic_warehouse/simulation/actions/material/insert_material/insert_random_material.py
automatic_warehouse/simulation/actions/material/remove_material/__init__.py
automatic_warehouse/simulation/actions/material/remove_material/remove_material.py
automatic_warehouse/simulation/actions/material/remove_material/remove_random_material.py
automatic_warehouse/simulation/actions/move/__init__.py
automatic_warehouse/simulation/actions/move/go_to_bay.py
automatic_warehouse/simulation/actions/move/go_to_buffer.py
automatic_warehouse/simulation/actions/move/load.py
automatic_warehouse/simulation/actions/move/move.py
automatic_warehouse/simulation/actions/move/unload.py
automatic_warehouse/simulation/actions/move/vertical.py
automatic_warehouse/simulation/simulation_type/__init__.py
automatic_warehouse/simulation/simulation_type/warehouse_simulation.py
automatic_warehouse/status_warehouse/__init__.py
automatic_warehouse/status_warehouse/material.py
automatic_warehouse/status_warehouse/tray.py
automatic_warehouse/status_warehouse/container/__init__.py
automatic_warehouse/status_warehouse/container/carousel.py
simulator_automatic_warehouse-1.0.4.dist-info/METADATA
simulator_automatic_warehouse-1.0.4.dist-info/WHEEL
simulator_automatic_warehouse-1.0.4.dist-info/licenses/LICENSE
simulator_automatic_warehouse-1.0.4.dist-info/RECORD
