Metadata-Version: 2.4
Name: simulator-automatic-warehouse
Version: 1.0.4
Summary: Simulator and Digital Twin of an Automatic Warehouse.
Project-URL: Documentation, https://simulator-automatic-warehouse.readthedocs.io/en/latest/
Project-URL: PyPI, https://pypi.org/project/simulator-automatic-warehouse
Project-URL: GitHub, https://github.com/AndreVale69/simulator-automatic-warehouse
Project-URL: Changelog, https://github.com/AndreVale69/simulator-automatic-warehouse/blob/main/CHANGELOG.md
Project-URL: Issues, https://github.com/AndreVale69/simulator-automatic-warehouse/issues
Author-email: Andrea Valentini <andrea.valentini.0000@gmail.com>
License-Expression: MIT
License-File: LICENSE
Keywords: automatic warehouse,digital twin,ferretto,simulator,simulator automatic warehouse,univr,vertimag,warehouse
Classifier: Development Status :: 5 - Production/Stable
Classifier: License :: OSI Approved :: MIT License
Classifier: Operating System :: MacOS
Classifier: Operating System :: Microsoft
Classifier: Operating System :: Unix
Classifier: Programming Language :: Python :: 3.9
Classifier: Programming Language :: Python :: 3.10
Classifier: Programming Language :: Python :: 3.11
Classifier: Programming Language :: Python :: 3.12
Classifier: Programming Language :: Python :: 3.13
Classifier: Programming Language :: Python :: 3.14
Requires-Python: >=3.9
Requires-Dist: jsonschema>=4.0.0
Requires-Dist: pandas>=2.2.0
Requires-Dist: pyyaml>=5.1
Requires-Dist: simpy>=3.0
